bgpy/__init__.py
bgpy/__main__.py
bgpy/enums.py
bgpy/py.typed
bgpy/as_graphs/__init__.py
bgpy/as_graphs/base/__init__.py
bgpy/as_graphs/base/as_graph_collector.py
bgpy/as_graphs/base/as_graph_constructor.py
bgpy/as_graphs/base/as_graph_info.py
bgpy/as_graphs/base/as_graph/__init__.py
bgpy/as_graphs/base/as_graph/as_graph.py
bgpy/as_graphs/base/as_graph/base_as.py
bgpy/as_graphs/base/as_graph/cone_funcs.py
bgpy/as_graphs/base/as_graph/customer_cone_funcs.py
bgpy/as_graphs/base/as_graph/graph_building_funcs.py
bgpy/as_graphs/base/as_graph/propagation_rank_funcs.py
bgpy/as_graphs/base/links/__init__.py
bgpy/as_graphs/base/links/customer_provider_link.py
bgpy/as_graphs/base/links/link.py
bgpy/as_graphs/base/links/peer_link.py
bgpy/as_graphs/caida_as_graph/__init__.py
bgpy/as_graphs/caida_as_graph/caida_as_graph.py
bgpy/as_graphs/caida_as_graph/caida_as_graph_collector.py
bgpy/as_graphs/caida_as_graph/caida_as_graph_constructor.py
bgpy/shared/__init__.py
bgpy/shared/constants.py
bgpy/shared/enums.py
bgpy/shared/exceptions.py
bgpy/simulation_engine/__init__.py
bgpy/simulation_engine/announcement.py
bgpy/simulation_engine/ann_containers/__init__.py
bgpy/simulation_engine/ann_containers/ann_container.py
bgpy/simulation_engine/ann_containers/local_rib.py
bgpy/simulation_engine/ann_containers/recv_queue.py
bgpy/simulation_engine/ann_containers/ribs_in.py
bgpy/simulation_engine/ann_containers/ribs_out.py
bgpy/simulation_engine/policies/__init__.py
bgpy/simulation_engine/policies/policy.py
bgpy/simulation_engine/policies/aspa/__init__.py
bgpy/simulation_engine/policies/aspa/aspa.py
bgpy/simulation_engine/policies/aspa/aspa_full.py
bgpy/simulation_engine/policies/aspa/aspawn.py
bgpy/simulation_engine/policies/aspa/aspawn_full.py
bgpy/simulation_engine/policies/aspa/asra.py
bgpy/simulation_engine/policies/aspa/asra_full.py
bgpy/simulation_engine/policies/bgp/__init__.py
bgpy/simulation_engine/policies/bgp/bgp_full.py
bgpy/simulation_engine/policies/bgp/bgp_full_ignore_invalid.py
bgpy_pkg-13.0.10.dist-info/licenses/LICENSE.txt
bgpy_pkg-13.0.10.dist-info/METADATA
bgpy_pkg-13.0.10.dist-info/WHEEL
bgpy_pkg-13.0.10.dist-info/entry_points.txt
bgpy_pkg-13.0.10.dist-info/top_level.txt
bgpy_pkg-13.0.10.dist-info/RECORD
