Metadata-Version: 2.4
Name: bgpy_pkg
Version: 13.0.10
Summary: Simulates BGP, ROV, ASPA, etc in an extensible manner
Author-email: Justin Furuness <jfuruness@gmail.com>, Cameron Morris <cameron.morris@uconn.edu>, Reynaldo Morillo <reynaldo.morillo@uconn.edu>, Arvind Kasiliya <arvind.kasiliya@uconn.edu>, Joel Braun <joelbraun@protonmail.com>
Maintainer-email: Justin Furuness <jfuruness@gmail.com>
License: Copyright 2020 Justin Furuness
Project-URL: Homepage, https://github.com/jfuruness/bgpy_pkg
Project-URL: Documentation, https://github.com/jfuruness/bgpy/wiki
Keywords: BGPy,bgpy,bgpc,bgpy_pkg,BGP,Caida,CAIDA,Peers,Providers,Relationships,AS-Serial,Customers,Simulation,ROV,Furuness
Classifier: Programming Language :: Python :: 3.10
Classifier: Programming Language :: Python :: 3.11
Classifier: Programming Language :: Python :: 3.12
Classifier: Programming Language :: Python :: 3.13
Classifier: Programming Language :: Python :: 3.14
Classifier: Programming Language :: Python :: Implementation :: CPython
Classifier: Programming Language :: Python :: Implementation :: PyPy
Classifier: Environment :: Console
Classifier: License :: OSI Approved :: MIT License
Classifier: Intended Audience :: Developers
Classifier: Operating System :: POSIX :: Linux
Classifier: Operating System :: MacOS
Classifier: Operating System :: MacOS :: MacOS X
Classifier: Topic :: Security
Requires-Python: >=3.10
License-File: LICENSE.txt
Requires-Dist: beautifulsoup4==4.14.3
Requires-Dist: frozendict==2.4.7
Requires-Dist: graphviz==0.21
Requires-Dist: matplotlib==3.10.8
Requires-Dist: platformdirs==4.5.1
Requires-Dist: psutil==7.2.1
Requires-Dist: pytest==9.0.2
Requires-Dist: PyYAML==6.0.3
Requires-Dist: requests==2.32.5
Requires-Dist: requests-cache==1.2.1
Requires-Dist: roa-checker~=3.0
Requires-Dist: rov-collector~=1.0
Requires-Dist: tqdm==4.67.1
Requires-Dist: yamlable==1.1.1
Provides-Extra: test
Requires-Dist: pytest==9.0.2; extra == "test"
Requires-Dist: pre-commit==4.5.1; extra == "test"
Requires-Dist: types-beautifulsoup4==4.12.0.20250516; extra == "test"
Requires-Dist: types-requests==2.32.4.20260107; extra == "test"
Requires-Dist: types-psutil==7.2.1.20260116; extra == "test"
Requires-Dist: types-PyYAML==6.0.12.20250915; extra == "test"
Requires-Dist: types-tqdm==4.67.0.20250809; extra == "test"
Requires-Dist: mypy==1.19.1; extra == "test"
Requires-Dist: tox==4.34.1; extra == "test"
Requires-Dist: pytest-xdist==3.8.0; extra == "test"
Requires-Dist: ruff==0.14.13; extra == "test"
Dynamic: license-file
